core/__init__.py
core/redfish_client.py
core/hwmonitor/__init__.py
core/hwmonitor/alert.py
core/hwmonitor/client.py
core/hwmonitor/types.py
core/ipmi/__init__.py
core/ipmi/client.py
core/ipmi/config/__init__.py
core/ipmi/config/bmc_config.py
core/ipmi/operations/__init__.py
core/ipmi/operations/fru.py
core/ipmi/operations/power.py
core/ipmi/operations/sel.py
core/ipmi/operations/sensors.py
core/ipmi/operations/sol.py
core/ipmi/operations/users.py
core/ipmi/protocols/__init__.py
core/ipmi/protocols/ipmi.py
core/ipmi/protocols/ipmi_protocol.py
core/provisioning/__init__.py
core/provisioning/deployment.py
core/provisioning/ipxe.py
core/provisioning/network.py
core/remoteconsole/__init__.py
core/remoteconsole/client.py
core/remoteconsole/types.py
core/remoteconsole/viewers.py
core/virtualmedia/__init__.py
core/virtualmedia/client.py
core/virtualmedia/operations.py
core/virtualmedia/types.py
greenfish-0.1.0.dist-info/licenses/LICENSE
ui/__init__.py
ui/dialogs/__init__.py
ui/dialogs/connection_dialog.py
ui/dialogs/profile_dialog.py
ui/dialogs/settings_dialog.py
ui/widgets/__init__.py
ui/widgets/account_widget.py
ui/widgets/bios_config_widget.py
ui/widgets/dashboard_widget.py
ui/widgets/event_subscription_widget.py
ui/widgets/firmware_widget.py
ui/widgets/log_widget.py
ui/widgets/network_config_widget.py
ui/widgets/secure_boot_widget.py
ui/widgets/system_info_widget.py
ui/widgets/task_monitor_widget.py
ui/widgets/user_management_widget.py
ui/widgets/virtual_media_widget.py
ui/widgets/metrics/__init__.py
ui/widgets/metrics/base_panel.py
ui/widgets/metrics/memory_metrics.py
ui/widgets/metrics/metrics_widget.py
ui/widgets/metrics/network_metrics.py
ui/widgets/metrics/power_metrics.py
ui/widgets/metrics/processor_metrics.py
ui/widgets/metrics/storage_metrics.py
ui/widgets/metrics/telemetry_panel.py
ui/widgets/metrics/thermal_metrics.py
greenfish-0.1.0.dist-info/METADATA
greenfish-0.1.0.dist-info/WHEEL
greenfish-0.1.0.dist-info/entry_points.txt
greenfish-0.1.0.dist-info/top_level.txt
greenfish-0.1.0.dist-info/RECORD
