Metadata-Version: 2.4
Name: greenfish
Version: 0.1.0
Summary: A Redfish and IPMI desktop client for out-of-band server management
Home-page: https://github.com/mexyusef/greenfish
Author: Yusef Ulum
Author-email: yusef314159@gmail.com
Project-URL: Bug Tracker, https://github.com/mexyusef/greenfish/issues
Project-URL: Source Code, https://github.com/mexyusef/greenfish
Classifier: Development Status :: 3 - Alpha
Classifier: Intended Audience :: System Administrators
Classifier: Intended Audience :: Information Technology
Classifier: Programming Language :: Python :: 3
Classifier: Programming Language :: Python :: 3.8
Classifier: Programming Language :: Python :: 3.9
Classifier: Programming Language :: Python :: 3.10
Classifier: Programming Language :: Python :: 3.11
Classifier: Operating System :: OS Independent
Classifier: Topic :: System :: Systems Administration
Classifier: Topic :: System :: Hardware
Classifier: Topic :: System :: Monitoring
Requires-Python: >=3.8
License-File: LICENSE
Requires-Dist: PyQt6>=6.4.0
Requires-Dist: redfish>=3.1.0
Requires-Dist: requests>=2.28.0
Requires-Dist: jsonpatch>=1.32
Requires-Dist: jsonpath-rw>=1.4.0
Requires-Dist: jsonpointer>=2.3
Requires-Dist: requests-toolbelt>=0.9.1
Requires-Dist: requests-unixsocket>=0.2.0
Requires-Dist: urllib3>=2.0.0
Requires-Dist: colorama>=0.4.6
Provides-Extra: dev
Requires-Dist: pytest>=7.0.0; extra == "dev"
Requires-Dist: pytest-cov>=4.0.0; extra == "dev"
Requires-Dist: black>=23.0.0; extra == "dev"
Requires-Dist: isort>=5.12.0; extra == "dev"
Requires-Dist: flake8>=6.0.0; extra == "dev"
Requires-Dist: mypy>=1.0.0; extra == "dev"
Requires-Dist: sphinx>=6.0.0; extra == "dev"
Requires-Dist: sphinx-rtd-theme>=1.2.0; extra == "dev"
Dynamic: author
Dynamic: author-email
Dynamic: classifier
Dynamic: description
Dynamic: description-content-type
Dynamic: home-page
Dynamic: license-file
Dynamic: project-url
Dynamic: provides-extra
Dynamic: requires-dist
Dynamic: requires-python
Dynamic: summary
